{
  "country": "France",
  "source": "World Bank World Development Indicators",
  "series": [
    {
      "sector": "Services",
      "indicator": "NV.SRV.TOTL.ZS",
      "values": [
        {
          "year": 2000,
          "value": 66.4177882404231
        },
        {
          "year": 2001,
          "value": 67.0215216824266
        },
        {
          "year": 2002,
          "value": 67.5410421037319
        },
        {
          "year": 2003,
          "value": 68.1890446774506
        },
        {
          "year": 2004,
          "value": 68.3406837903041
        },
        {
          "year": 2005,
          "value": 68.7116075234513
        },
        {
          "year": 2006,
          "value": 68.9051445140813
        },
        {
          "year": 2007,
          "value": 69.1752306377863
        },
        {
          "year": 2008,
          "value": 69.7683271007528
        },
        {
          "year": 2009,
          "value": 70.8157987420656
        },
        {
          "year": 2010,
          "value": 70.7106511172851
        },
        {
          "year": 2011,
          "value": 70.2766502820806
        },
        {
          "year": 2012,
          "value": 70.3954825743036
        },
        {
          "year": 2013,
          "value": 70.4096711493974
        },
        {
          "year": 2014,
          "value": 70.4282438710721
        },
        {
          "year": 2015,
          "value": 70.3090113135195
        },
        {
          "year": 2016,
          "value": 70.602995081322
        },
        {
          "year": 2017,
          "value": 70.3851824021717
        },
        {
          "year": 2018,
          "value": 70.1367025071467
        },
        {
          "year": 2019,
          "value": 70.1101608629661
        },
        {
          "year": 2020,
          "value": 70.9770173200242
        },
        {
          "year": 2021,
          "value": 70.6735726050728
        },
        {
          "year": 2022,
          "value": 71.3378674303834
        },
        {
          "year": 2023,
          "value": 69.6610779850985
        },
        {
          "year": 2024,
          "value": 70.4000374065717
        }
      ]
    },
    {
      "sector": "Industrie",
      "indicator": "NV.IND.TOTL.ZS",
      "values": [
        {
          "year": 2000,
          "value": 21.1286830497341
        },
        {
          "year": 2001,
          "value": 20.764024725913
        },
        {
          "year": 2002,
          "value": 20.3641075404744
        },
        {
          "year": 2003,
          "value": 19.9232786673445
        },
        {
          "year": 2004,
          "value": 19.6686920294036
        },
        {
          "year": 2005,
          "value": 19.3552308487449
        },
        {
          "year": 2006,
          "value": 19.0188918781413
        },
        {
          "year": 2007,
          "value": 18.8988946301681
        },
        {
          "year": 2008,
          "value": 18.6335203970131
        },
        {
          "year": 2009,
          "value": 18.0198241569733
        },
        {
          "year": 2010,
          "value": 17.5945885002022
        },
        {
          "year": 2011,
          "value": 17.6800048726048
        },
        {
          "year": 2012,
          "value": 17.4684347699959
        },
        {
          "year": 2013,
          "value": 17.5699939241217
        },
        {
          "year": 2014,
          "value": 17.3416195349368
        },
        {
          "year": 2015,
          "value": 17.236441547058
        },
        {
          "year": 2016,
          "value": 16.9433572396904
        },
        {
          "year": 2017,
          "value": 16.7483032647876
        },
        {
          "year": 2018,
          "value": 16.725283255726
        },
        {
          "year": 2019,
          "value": 16.907003960354
        },
        {
          "year": 2020,
          "value": 16.272651205236
        },
        {
          "year": 2021,
          "value": 16.0877289574672
        },
        {
          "year": 2022,
          "value": 16.1980918380604
        },
        {
          "year": 2023,
          "value": 18.4701925763483
        },
        {
          "year": 2024,
          "value": 17.5480122316203
        }
      ]
    },
    {
      "sector": "Agriculture",
      "indicator": "NV.AGR.TOTL.ZS",
      "values": [
        {
          "year": 2000,
          "value": 1.98449655121117
        },
        {
          "year": 2001,
          "value": 2.00226015670254
        },
        {
          "year": 2002,
          "value": 1.90378389721189
        },
        {
          "year": 2003,
          "value": 1.74560664256609
        },
        {
          "year": 2004,
          "value": 1.72018557547967
        },
        {
          "year": 2005,
          "value": 1.58270403235962
        },
        {
          "year": 2006,
          "value": 1.42706409375236
        },
        {
          "year": 2007,
          "value": 1.516727357675
        },
        {
          "year": 2008,
          "value": 1.42030674677991
        },
        {
          "year": 2009,
          "value": 1.23241577481447
        },
        {
          "year": 2010,
          "value": 1.50088040274637
        },
        {
          "year": 2011,
          "value": 1.55137276231397
        },
        {
          "year": 2012,
          "value": 1.52594468949115
        },
        {
          "year": 2013,
          "value": 1.36140137870511
        },
        {
          "year": 2014,
          "value": 1.46154600121993
        },
        {
          "year": 2015,
          "value": 1.50360116027898
        },
        {
          "year": 2016,
          "value": 1.33798472564444
        },
        {
          "year": 2017,
          "value": 1.43496006533197
        },
        {
          "year": 2018,
          "value": 1.53110170543578
        },
        {
          "year": 2019,
          "value": 1.40828485472535
        },
        {
          "year": 2020,
          "value": 1.4604342657704
        },
        {
          "year": 2021,
          "value": 1.46334541457898
        },
        {
          "year": 2022,
          "value": 1.76309719499818
        },
        {
          "year": 2023,
          "value": 1.74050275246234
        },
        {
          "year": 2024,
          "value": 1.4317153097006
        }
      ]
    }
  ]
}